session_security/__init__.py
session_security/middleware.py
session_security/models.py
session_security/settings.py
session_security/urls.py
session_security/utils.py
session_security/views.py
session_security/locale/ca/LC_MESSAGES/django.mo
session_security/locale/ca/LC_MESSAGES/django.po
session_security/locale/cs/LC_MESSAGES/django.mo
session_security/locale/cs/LC_MESSAGES/django.po
session_security/locale/es/LC_MESSAGES/django.mo
session_security/locale/es/LC_MESSAGES/django.po
session_security/locale/fr/LC_MESSAGES/django.mo
session_security/locale/fr/LC_MESSAGES/django.po
session_security/locale/it/LC_MESSAGES/django.mo
session_security/locale/it/LC_MESSAGES/django.po
session_security/locale/nl/LC_MESSAGES/django.mo
session_security/locale/nl/LC_MESSAGES/django.po
session_security/locale/pl/LC_MESSAGES/django.mo
session_security/locale/pl/LC_MESSAGES/django.po
session_security/locale/pt_BR/LC_MESSAGES/django.mo
session_security/locale/pt_BR/LC_MESSAGES/django.po
session_security/locale/pt_PT/LC_MESSAGES/django.mo
session_security/locale/pt_PT/LC_MESSAGES/django.po
session_security/static/session_security/script.js
session_security/static/session_security/style.css
session_security/templates/session_security/all.html
session_security/templates/session_security/dialog.html
session_security/templatetags/__init__.py
session_security/templatetags/session_security_tags.py
session_security/tests/__init__.py
session_security/tests/test_base.py
session_security/tests/test_middleware.py
session_security/tests/test_script.py
session_security/tests/test_views.py
session_security/tests/project/__init__.py
session_security/tests/project/settings.py
session_security/tests/project/urls.py
session_security/tests/project/wsgi.py
session_security/tests/project/static/jquery.js
session_security/tests/project/templates/404.html
session_security/tests/project/templates/500.html
session_security/tests/project/templates/home.html
django_session_security-2.6.7.dist-info/AUTHORS
django_session_security-2.6.7.dist-info/LICENSE
django_session_security-2.6.7.dist-info/METADATA
django_session_security-2.6.7.dist-info/WHEEL
django_session_security-2.6.7.dist-info/top_level.txt
django_session_security-2.6.7.dist-info/RECORD
